[
  {
    "user": {
      "first_name": "Joshua",
      "last_name": "Measey",
      "email": "jmeasey0@independent.co.uk",
      "phone": "8817869697"
    },
    "address": {
      "street_address": "1 Mcbride Junction",
      "city": "Sydney",
      "state": "New South Wales",
      "region_code": "NSW",
      "postal_code": "1009"
    }
  },
  {
    "user": {
      "first_name": "Rufus",
      "last_name": "Dictus",
      "email": "rdictus0@a8.net",
      "phone": "7795760189"
    },
    "address": {
      "street_address": "15971 Pennsylvania Street",
      "city": "Sydney",
      "state": "New South Wales",
      "region_code": "NSW",
      "postal_code": "1120"
    }
  },
  {
    "user": {
      "first_name": "Hyatt",
      "last_name": "Hesse",
      "email": "hhesse0@wikia.com",
      "phone": "6198859254"
    },
    "address": {
      "street_address": "0 Hagan Lane",
      "city": "Northern Suburbs Mc",
      "state": "New South Wales",
      "region_code": "NSW",
      "postal_code": "1694"
    }
  },
  {
    "user": {
      "first_name": "Nicol",
      "last_name": "Pautard",
      "email": "npautard0@who.int",
      "phone": "7041178203"
    },
    "address": {
      "street_address": "7329 Meadow Ridge Point",
      "city": "Australia Square",
      "state": "New South Wales",
      "region_code": "NSW",
      "postal_code": "1213"
    }
  },
  {
    "user": {
      "first_name": "Nita",
      "last_name": "Dimitrescu",
      "email": "ndimitrescu0@shop-pro.jp",
      "phone": "6608327558"
    },
    "address": {
      "street_address": "12633 Kings Crossing",
      "city": "Northern Suburbs Mc",
      "state": "New South Wales",
      "region_code": "NSW",
      "postal_code": "1694"
    }
  },
  {
    "user": {
      "first_name": "Halimeda",
      "last_name": "Fearnley",
      "email": "hfearnley0@histats.com",
      "phone": "9472216419"
    },
    "address": {
      "street_address": "2733 Barnett Avenue",
      "city": "Hobart",
      "state": "Tasmania",
      "region_code": "TAS",
      "postal_code": "7808"
    }
  },
  {
    "user": {
      "first_name": "Eunice",
      "last_name": "Phythien",
      "email": "ephythien0@stanford.edu",
      "phone": "8717436230"
    },
    "address": {
      "street_address": "94 Columbus Avenue",
      "city": "Sydney",
      "state": "New South Wales",
      "region_code": "NSW",
      "postal_code": "1033"
    }
  },
  {
    "user": {
      "first_name": "Iorgos",
      "last_name": "Denys",
      "email": "idenys0@devhub.com",
      "phone": "7311603943"
    },
    "address": {
      "street_address": "25294 Aberg Road",
      "city": "Eastern Suburbs Mc",
      "state": "New South Wales",
      "region_code": "NSW",
      "postal_code": "1325"
    }
  },
  {
    "user": {
      "first_name": "Olva",
      "last_name": "Gillman",
      "email": "ogillman0@ocn.ne.jp",
      "phone": "5445989784"
    },
    "address": {
      "street_address": "52 Sauthoff Trail",
      "city": "Sydney",
      "state": "New South Wales",
      "region_code": "NSW",
      "postal_code": "1009"
    }
  },
  {
    "user": {
      "first_name": "Lance",
      "last_name": "Mioni",
      "email": "lmioni0@hao123.com",
      "phone": "7833171816"
    },
    "address": {
      "street_address": "38 Eggendart Road",
      "city": "Adelaide Mail Centre",
      "state": "South Australia",
      "region_code": "SA",
      "postal_code": "5869"
    }
  },
  {
    "user": {
      "first_name": "Yuri",
      "last_name": "Winsley",
      "email": "ywinsley0@unblog.fr",
      "phone": "9143606559"
    },
    "address": {
      "street_address": "382 Ronald Regan Court",
      "city": "Launceston",
      "state": "Tasmania",
      "region_code": "TAS",
      "postal_code": "7904"
    }
  },
  {
    "user": {
      "first_name": "Les",
      "last_name": "Drury",
      "email": "ldrury0@bigcartel.com",
      "phone": "3264386916"
    },
    "address": {
      "street_address": "03 Kings Terrace",
      "city": "Sydney",
      "state": "New South Wales",
      "region_code": "NSW",
      "postal_code": "1109"
    }
  },
  {
    "user": {
      "first_name": "Pearla",
      "last_name": "Eykelbosch",
      "email": "peykelbosch0@wikimedia.org",
      "phone": "4628788398"
    },
    "address": {
      "street_address": "8 Mayfield Crossing",
      "city": "Australia Square",
      "state": "New South Wales",
      "region_code": "NSW",
      "postal_code": "1213"
    }
  },
  {
    "user": {
      "first_name": "Puff",
      "last_name": "Talby",
      "email": "ptalby0@bing.com",
      "phone": "4046411250"
    },
    "address": {
      "street_address": "60718 Elmside Avenue",
      "city": "Eastern Suburbs Mc",
      "state": "New South Wales",
      "region_code": "NSW",
      "postal_code": "1325"
    }
  },
  {
    "user": {
      "first_name": "Jozef",
      "last_name": "Ginnally",
      "email": "jginnally0@weebly.com",
      "phone": "2183943579"
    },
    "address": {
      "street_address": "89280 Mesta Junction",
      "city": "Sydney",
      "state": "New South Wales",
      "region_code": "NSW",
      "postal_code": "1181"
    }
  },
  {
    "user": {
      "first_name": "Thurstan",
      "last_name": "Murkin",
      "email": "tmurkin0@photobucket.com",
      "phone": "1278448619"
    },
    "address": {
      "street_address": "42567 Lillian Lane",
      "city": "Sydney",
      "state": "New South Wales",
      "region_code": "NSW",
      "postal_code": "1171"
    }
  },
  {
    "user": {
      "first_name": "Regen",
      "last_name": "Messham",
      "email": "rmessham0@ovh.net",
      "phone": "6942473101"
    },
    "address": {
      "street_address": "1 American Ash Parkway",
      "city": "Adelaide Mail Centre",
      "state": "South Australia",
      "region_code": "SA",
      "postal_code": "5889"
    }
  },
  {
    "user": {
      "first_name": "Celestyn",
      "last_name": "McMenamy",
      "email": "cmcmenamy0@cmu.edu",
      "phone": "6556547661"
    },
    "address": {
      "street_address": "8909 Hansons Hill",
      "city": "Eastern Suburbs Mc",
      "state": "New South Wales",
      "region_code": "NSW",
      "postal_code": "1391"
    }
  },
  {
    "user": {
      "first_name": "Kellen",
      "last_name": "Brooks",
      "email": "kbrooks0@sogou.com",
      "phone": "9172652771"
    },
    "address": {
      "street_address": "11575 Union Avenue",
      "city": "Sydney South",
      "state": "New South Wales",
      "region_code": "NSW",
      "postal_code": "1235"
    }
  },
  {
    "user": {
      "first_name": "Matty",
      "last_name": "Python",
      "email": "mpython0@patch.com",
      "phone": "5703942617"
    },
    "address": {
      "street_address": "63 Talisman Park",
      "city": "Perth",
      "state": "Western Australia",
      "region_code": "WA",
      "postal_code": "6843"
    }
  },
  {
    "user": {
      "first_name": "Etienne",
      "last_name": "Pinckney",
      "email": "epinckney0@acquirethisname.com",
      "phone": "2329077729"
    },
    "address": {
      "street_address": "3301 Beilfuss Terrace",
      "city": "Eastern Suburbs Mc",
      "state": "New South Wales",
      "region_code": "NSW",
      "postal_code": "1325"
    }
  },
  {
    "user": {
      "first_name": "Gianna",
      "last_name": "Francioli",
      "email": "gfrancioli0@yellowpages.com",
      "phone": "4768099425"
    },
    "address": {
      "street_address": "4 Golf View Circle",
      "city": "Eastern Suburbs Mc",
      "state": "New South Wales",
      "region_code": "NSW",
      "postal_code": "1391"
    }
  },
  {
    "user": {
      "first_name": "Trudi",
      "last_name": "Acom",
      "email": "tacom0@hostgator.com",
      "phone": "1836537912"
    },
    "address": {
      "street_address": "89 Nelson Circle",
      "city": "Eastern Suburbs Mc",
      "state": "New South Wales",
      "region_code": "NSW",
      "postal_code": "1315"
    }
  },
  {
    "user": {
      "first_name": "Emmalyn",
      "last_name": "Heamus",
      "email": "eheamus0@storify.com",
      "phone": "5562811379"
    },
    "address": {
      "street_address": "5174 Dorton Center",
      "city": "Sydney",
      "state": "New South Wales",
      "region_code": "NSW",
      "postal_code": "1181"
    }
  },
  {
    "user": {
      "first_name": "Cornall",
      "last_name": "Jerzykiewicz",
      "email": "cjerzykiewicz0@admin.ch",
      "phone": "3518008063"
    },
    "address": {
      "street_address": "986 Glendale Street",
      "city": "Sydney",
      "state": "New South Wales",
      "region_code": "NSW",
      "postal_code": "1033"
    }
  },
  {
    "user": {
      "first_name": "Harli",
      "last_name": "Ranyell",
      "email": "hranyell0@icq.com",
      "phone": "4228661772"
    },
    "address": {
      "street_address": "50029 Anthes Park",
      "city": "Perth",
      "state": "Western Australia",
      "region_code": "WA",
      "postal_code": "6817"
    }
  },
  {
    "user": {
      "first_name": "Lind",
      "last_name": "Dashper",
      "email": "ldashper0@harvard.edu",
      "phone": "9057868446"
    },
    "address": {
      "street_address": "5 Northridge Way",
      "city": "Perth",
      "state": "Western Australia",
      "region_code": "WA",
      "postal_code": "6817"
    }
  },
  {
    "user": {
      "first_name": "Dorette",
      "last_name": "Flohard",
      "email": "dflohard0@soup.io",
      "phone": "8601999923"
    },
    "address": {
      "street_address": "71676 Novick Road",
      "city": "Sydney",
      "state": "New South Wales",
      "region_code": "NSW",
      "postal_code": "1043"
    }
  },
  {
    "user": {
      "first_name": "Helenelizabeth",
      "last_name": "McGahey",
      "email": "hmcgahey0@vistaprint.com",
      "phone": "6253691178"
    },
    "address": {
      "street_address": "8147 Carioca Place",
      "city": "Adelaide Mail Centre",
      "state": "South Australia",
      "region_code": "SA",
      "postal_code": "5874"
    }
  },
  {
    "user": {
      "first_name": "Gill",
      "last_name": "Tiddy",
      "email": "gtiddy0@quantcast.com",
      "phone": "4253762496"
    },
    "address": {
      "street_address": "01903 Blue Bill Park Lane",
      "city": "Sydney",
      "state": "New South Wales",
      "region_code": "NSW",
      "postal_code": "1033"
    }
  },
  {
    "user": {
      "first_name": "Carlynn",
      "last_name": "Hackney",
      "email": "chackney0@addtoany.com",
      "phone": "5105551938"
    },
    "address": {
      "street_address": "70218 Evergreen Parkway",
      "city": "Sydney",
      "state": "New South Wales",
      "region_code": "NSW",
      "postal_code": "1028"
    }
  },
  {
    "user": {
      "first_name": "Anni",
      "last_name": "McTear",
      "email": "amctear0@mapquest.com",
      "phone": "1936819048"
    },
    "address": {
      "street_address": "5 Graedel Avenue",
      "city": "Melbourne",
      "state": "Victoria",
      "region_code": "VIC",
      "postal_code": "8383"
    }
  },
  {
    "user": {
      "first_name": "Kathlin",
      "last_name": "Sallan",
      "email": "ksallan0@1688.com",
      "phone": "3533563389"
    },
    "address": {
      "street_address": "0400 Superior Street",
      "city": "Sydney",
      "state": "New South Wales",
      "region_code": "NSW",
      "postal_code": "1109"
    }
  },
  {
    "user": {
      "first_name": "Addi",
      "last_name": "Antonias",
      "email": "aantonias0@webeden.co.uk",
      "phone": "2193500663"
    },
    "address": {
      "street_address": "45058 Esch Park",
      "city": "Sydney",
      "state": "New South Wales",
      "region_code": "NSW",
      "postal_code": "1196"
    }
  },
  {
    "user": {
      "first_name": "Celestia",
      "last_name": "Van Vuuren",
      "email": "cvanvuuren0@indiegogo.com",
      "phone": "3929069754"
    },
    "address": {
      "street_address": "2 Stang Alley",
      "city": "Perth",
      "state": "Western Australia",
      "region_code": "WA",
      "postal_code": "6843"
    }
  },
  {
    "user": {
      "first_name": "Cirilo",
      "last_name": "Akers",
      "email": "cakers0@digg.com",
      "phone": "9295961461"
    },
    "address": {
      "street_address": "1 Mcbride Parkway",
      "city": "Adelaide Mail Centre",
      "state": "South Australia",
      "region_code": "SA",
      "postal_code": "5874"
    }
  },
  {
    "user": {
      "first_name": "Klarika",
      "last_name": "Backen",
      "email": "kbacken0@cloudflare.com",
      "phone": "9052311888"
    },
    "address": {
      "street_address": "5 Duke Hill",
      "city": "Brisbane",
      "state": "Queensland",
      "region_code": "QLD",
      "postal_code": "9010"
    }
  },
  {
    "user": {
      "first_name": "Georg",
      "last_name": "Dagwell",
      "email": "gdagwell0@amazon.com",
      "phone": "8393246929"
    },
    "address": {
      "street_address": "600 Maywood Junction",
      "city": "Sydney",
      "state": "New South Wales",
      "region_code": "NSW",
      "postal_code": "1140"
    }
  },
  {
    "user": {
      "first_name": "Harriet",
      "last_name": "Artharg",
      "email": "hartharg0@jugem.jp",
      "phone": "1615205790"
    },
    "address": {
      "street_address": "5 Petterle Plaza",
      "city": "Sydney",
      "state": "New South Wales",
      "region_code": "NSW",
      "postal_code": "1028"
    }
  },
  {
    "user": {
      "first_name": "Othelia",
      "last_name": "Billingsley",
      "email": "obillingsley0@buzzfeed.com",
      "phone": "8657658190"
    },
    "address": {
      "street_address": "0 Manufacturers Place",
      "city": "Sydney",
      "state": "New South Wales",
      "region_code": "NSW",
      "postal_code": "1130"
    }
  },
  {
    "user": {
      "first_name": "Ceil",
      "last_name": "Ruttgers",
      "email": "cruttgers0@europa.eu",
      "phone": "3595132208"
    },
    "address": {
      "street_address": "795 Westridge Alley",
      "city": "Sydney",
      "state": "New South Wales",
      "region_code": "NSW",
      "postal_code": "1161"
    }
  },
  {
    "user": {
      "first_name": "Alysa",
      "last_name": "Leaning",
      "email": "aleaning0@psu.edu",
      "phone": "6547035396"
    },
    "address": {
      "street_address": "3 Fairfield Crossing",
      "city": "Sydney",
      "state": "New South Wales",
      "region_code": "NSW",
      "postal_code": "1130"
    }
  },
  {
    "user": {
      "first_name": "Sharleen",
      "last_name": "Gepheart",
      "email": "sgepheart0@timesonline.co.uk",
      "phone": "4934997504"
    },
    "address": {
      "street_address": "171 Stoughton Avenue",
      "city": "Sydney",
      "state": "New South Wales",
      "region_code": "NSW",
      "postal_code": "1033"
    }
  },
  {
    "user": {
      "first_name": "Ethelda",
      "last_name": "Keepence",
      "email": "ekeepence0@odnoklassniki.ru",
      "phone": "5704550714"
    },
    "address": {
      "street_address": "59334 Fisk Park",
      "city": "Sydney",
      "state": "New South Wales",
      "region_code": "NSW",
      "postal_code": "1191"
    }
  },
  {
    "user": {
      "first_name": "Steffen",
      "last_name": "Lednor",
      "email": "slednor0@feedburner.com",
      "phone": "7278254787"
    },
    "address": {
      "street_address": "470 Rockefeller Park",
      "city": "Northern Suburbs Mc",
      "state": "New South Wales",
      "region_code": "NSW",
      "postal_code": "1694"
    }
  },
  {
    "user": {
      "first_name": "Alec",
      "last_name": "Hutfield",
      "email": "ahutfield0@slideshare.net",
      "phone": "3315993619"
    },
    "address": {
      "street_address": "97429 Ilene Park",
      "city": "Melbourne",
      "state": "Victoria",
      "region_code": "VIC",
      "postal_code": "8383"
    }
  },
  {
    "user": {
      "first_name": "Gaultiero",
      "last_name": "Asbury",
      "email": "gasbury0@scientificamerican.com",
      "phone": "3453642861"
    },
    "address": {
      "street_address": "5 Sachs Drive",
      "city": "Eastern Suburbs Mc",
      "state": "New South Wales",
      "region_code": "NSW",
      "postal_code": "1325"
    }
  },
  {
    "user": {
      "first_name": "Olly",
      "last_name": "Whyteman",
      "email": "owhyteman0@yandex.ru",
      "phone": "9666926824"
    },
    "address": {
      "street_address": "13 Cottonwood Lane",
      "city": "Sydney South",
      "state": "New South Wales",
      "region_code": "NSW",
      "postal_code": "1235"
    }
  },
  {
    "user": {
      "first_name": "Umberto",
      "last_name": "Owbridge",
      "email": "uowbridge0@reference.com",
      "phone": "6448977701"
    },
    "address": {
      "street_address": "67 Mandrake Lane",
      "city": "Launceston",
      "state": "Tasmania",
      "region_code": "TAS",
      "postal_code": "7916"
    }
  },
  {
    "user": {
      "first_name": "Honor",
      "last_name": "Bennison",
      "email": "hbennison0@quantcast.com",
      "phone": "3844460522"
    },
    "address": {
      "street_address": "43604 5th Circle",
      "city": "Sydney",
      "state": "New South Wales",
      "region_code": "NSW",
      "postal_code": "1161"
    }
  },
  {
    "user": {
      "first_name": "Arabella",
      "last_name": "Fleet",
      "email": "afleet0@cargocollective.com",
      "phone": "6978249362"
    },
    "address": {
      "street_address": "6660 Northfield Drive",
      "city": "Adelaide Mail Centre",
      "state": "South Australia",
      "region_code": "SA",
      "postal_code": "5869"
    }
  },
  {
    "user": {
      "first_name": "Dorice",
      "last_name": "Lace",
      "email": "dlace0@latimes.com",
      "phone": "7773437411"
    },
    "address": {
      "street_address": "1777 Katie Hill",
      "city": "Sydney",
      "state": "New South Wales",
      "region_code": "NSW",
      "postal_code": "1130"
    }
  },
  {
    "user": {
      "first_name": "Marrilee",
      "last_name": "Applin",
      "email": "mapplin0@xrea.com",
      "phone": "1056993485"
    },
    "address": {
      "street_address": "188 Cottonwood Junction",
      "city": "Sydney",
      "state": "New South Wales",
      "region_code": "NSW",
      "postal_code": "1171"
    }
  },
  {
    "user": {
      "first_name": "Jose",
      "last_name": "Melbourne",
      "email": "jmelbourne0@loc.gov",
      "phone": "5852625064"
    },
    "address": {
      "street_address": "351 Fisk Court",
      "city": "Launceston",
      "state": "Tasmania",
      "region_code": "TAS",
      "postal_code": "7916"
    }
  },
  {
    "user": {
      "first_name": "Grove",
      "last_name": "Serginson",
      "email": "gserginson0@w3.org",
      "phone": "6676835725"
    },
    "address": {
      "street_address": "4 Cody Point",
      "city": "Eastern Suburbs Mc",
      "state": "New South Wales",
      "region_code": "NSW",
      "postal_code": "1325"
    }
  },
  {
    "user": {
      "first_name": "Bron",
      "last_name": "Thurston",
      "email": "bthurston0@springer.com",
      "phone": "2775131259"
    },
    "address": {
      "street_address": "6 Butterfield Street",
      "city": "Eastern Suburbs Mc",
      "state": "New South Wales",
      "region_code": "NSW",
      "postal_code": "1391"
    }
  },
  {
    "user": {
      "first_name": "Keefer",
      "last_name": "Dismore",
      "email": "kdismore0@networksolutions.com",
      "phone": "5668543713"
    },
    "address": {
      "street_address": "77 Burrows Drive",
      "city": "Sydney",
      "state": "New South Wales",
      "region_code": "NSW",
      "postal_code": "1191"
    }
  },
  {
    "user": {
      "first_name": "Alla",
      "last_name": "Heild",
      "email": "aheild0@psu.edu",
      "phone": "6067744773"
    },
    "address": {
      "street_address": "116 Melody Center",
      "city": "Sydney",
      "state": "New South Wales",
      "region_code": "NSW",
      "postal_code": "1033"
    }
  },
  {
    "user": {
      "first_name": "Erminia",
      "last_name": "Culwen",
      "email": "eculwen0@phoca.cz",
      "phone": "9512475183"
    },
    "address": {
      "street_address": "8 Acker Drive",
      "city": "Sydney",
      "state": "New South Wales",
      "region_code": "NSW",
      "postal_code": "1033"
    }
  },
  {
    "user": {
      "first_name": "Zachary",
      "last_name": "Downage",
      "email": "zdownage0@ucoz.ru",
      "phone": "7843859392"
    },
    "address": {
      "street_address": "5353 Farmco Alley",
      "city": "Melbourne",
      "state": "Victoria",
      "region_code": "VIC",
      "postal_code": "8383"
    }
  },
  {
    "user": {
      "first_name": "Kellsie",
      "last_name": "Karpets",
      "email": "kkarpets0@huffingtonpost.com",
      "phone": "3024007903"
    },
    "address": {
      "street_address": "4629 Nelson Parkway",
      "city": "Perth",
      "state": "Western Australia",
      "region_code": "WA",
      "postal_code": "6843"
    }
  },
  {
    "user": {
      "first_name": "Valeda",
      "last_name": "Ovesen",
      "email": "vovesen0@gov.uk",
      "phone": "7458434099"
    },
    "address": {
      "street_address": "9 Brown Point",
      "city": "Sydney",
      "state": "New South Wales",
      "region_code": "NSW",
      "postal_code": "1161"
    }
  },
  {
    "user": {
      "first_name": "Yorgo",
      "last_name": "Macieiczyk",
      "email": "ymacieiczyk0@irs.gov",
      "phone": "8529267242"
    },
    "address": {
      "street_address": "8 Spohn Parkway",
      "city": "Sydney",
      "state": "New South Wales",
      "region_code": "NSW",
      "postal_code": "1130"
    }
  },
  {
    "user": {
      "first_name": "Christoffer",
      "last_name": "Stratiff",
      "email": "cstratiff0@desdev.cn",
      "phone": "7291504243"
    },
    "address": {
      "street_address": "4 Monterey Pass",
      "city": "Sydney",
      "state": "New South Wales",
      "region_code": "NSW",
      "postal_code": "1130"
    }
  },
  {
    "user": {
      "first_name": "Jude",
      "last_name": "Kopfen",
      "email": "jkopfen0@guardian.co.uk",
      "phone": "6712295758"
    },
    "address": {
      "street_address": "45221 Brickson Park Circle",
      "city": "Sydney",
      "state": "New South Wales",
      "region_code": "NSW",
      "postal_code": "1161"
    }
  },
  {
    "user": {
      "first_name": "Karita",
      "last_name": "Yaxley",
      "email": "kyaxley0@ameblo.jp",
      "phone": "2969027271"
    },
    "address": {
      "street_address": "18 Pankratz Pass",
      "city": "Sydney",
      "state": "New South Wales",
      "region_code": "NSW",
      "postal_code": "1140"
    }
  },
  {
    "user": {
      "first_name": "Mirella",
      "last_name": "Surpliss",
      "email": "msurpliss0@archive.org",
      "phone": "5897306521"
    },
    "address": {
      "street_address": "7192 Amoth Court",
      "city": "Adelaide Mail Centre",
      "state": "South Australia",
      "region_code": "SA",
      "postal_code": "5874"
    }
  },
  {
    "user": {
      "first_name": "Jayme",
      "last_name": "Inold",
      "email": "jinold0@nsw.gov.au",
      "phone": "6581282832"
    },
    "address": {
      "street_address": "2904 Randy Circle",
      "city": "Sydney",
      "state": "New South Wales",
      "region_code": "NSW",
      "postal_code": "1171"
    }
  },
  {
    "user": {
      "first_name": "August",
      "last_name": "Gillet",
      "email": "agillet0@livejournal.com",
      "phone": "7601802328"
    },
    "address": {
      "street_address": "80 Red Cloud Hill",
      "city": "Sydney",
      "state": "New South Wales",
      "region_code": "NSW",
      "postal_code": "1130"
    }
  },
  {
    "user": {
      "first_name": "Ardith",
      "last_name": "Rodson",
      "email": "arodson0@tiny.cc",
      "phone": "8411634113"
    },
    "address": {
      "street_address": "53685 Old Shore Crossing",
      "city": "Eastern Suburbs Mc",
      "state": "New South Wales",
      "region_code": "NSW",
      "postal_code": "1315"
    }
  },
  {
    "user": {
      "first_name": "Jud",
      "last_name": "Blakeden",
      "email": "jblakeden0@unicef.org",
      "phone": "7597291767"
    },
    "address": {
      "street_address": "177 Clarendon Court",
      "city": "Sydney",
      "state": "New South Wales",
      "region_code": "NSW",
      "postal_code": "1134"
    }
  },
  {
    "user": {
      "first_name": "Jacinthe",
      "last_name": "Mole",
      "email": "jmole0@yellowbook.com",
      "phone": "3204903272"
    },
    "address": {
      "street_address": "71357 Nelson Alley",
      "city": "Melbourne",
      "state": "Victoria",
      "region_code": "VIC",
      "postal_code": "8383"
    }
  },
  {
    "user": {
      "first_name": "Olag",
      "last_name": "Tax",
      "email": "otax0@nature.com",
      "phone": "3686513513"
    },
    "address": {
      "street_address": "89 Fuller Terrace",
      "city": "Sydney",
      "state": "New South Wales",
      "region_code": "NSW",
      "postal_code": "1120"
    }
  },
  {
    "user": {
      "first_name": "Egor",
      "last_name": "Mycock",
      "email": "emycock0@aboutads.info",
      "phone": "1848509971"
    },
    "address": {
      "street_address": "3448 Kingsford Hill",
      "city": "Hobart",
      "state": "Tasmania",
      "region_code": "TAS",
      "postal_code": "7803"
    }
  },
  {
    "user": {
      "first_name": "Tanney",
      "last_name": "Bricket",
      "email": "tbricket0@shinystat.com",
      "phone": "1537775165"
    },
    "address": {
      "street_address": "43336 Mallard Avenue",
      "city": "Sydney",
      "state": "New South Wales",
      "region_code": "NSW",
      "postal_code": "1028"
    }
  },
  {
    "user": {
      "first_name": "Minnie",
      "last_name": "Dohr",
      "email": "mdohr0@storify.com",
      "phone": "8248087473"
    },
    "address": {
      "street_address": "8131 Hayes Road",
      "city": "Eastern Suburbs Mc",
      "state": "New South Wales",
      "region_code": "NSW",
      "postal_code": "1325"
    }
  },
  {
    "user": {
      "first_name": "Tripp",
      "last_name": "De Bernardis",
      "email": "tdebernardis0@edublogs.org",
      "phone": "5534599697"
    },
    "address": {
      "street_address": "9 Monica Circle",
      "city": "Adelaide",
      "state": "South Australia",
      "region_code": "SA",
      "postal_code": "5839"
    }
  },
  {
    "user": {
      "first_name": "Leta",
      "last_name": "Blunsom",
      "email": "lblunsom0@wp.com",
      "phone": "9709735012"
    },
    "address": {
      "street_address": "09 American Pass",
      "city": "Sydney",
      "state": "New South Wales",
      "region_code": "NSW",
      "postal_code": "1109"
    }
  },
  {
    "user": {
      "first_name": "Bird",
      "last_name": "Perrot",
      "email": "bperrot0@about.com",
      "phone": "5399973761"
    },
    "address": {
      "street_address": "24572 Bellgrove Circle",
      "city": "Adelaide Mail Centre",
      "state": "South Australia",
      "region_code": "SA",
      "postal_code": "5889"
    }
  },
  {
    "user": {
      "first_name": "Johnathon",
      "last_name": "Urion",
      "email": "jurion0@nbcnews.com",
      "phone": "6456490604"
    },
    "address": {
      "street_address": "82774 Sage Road",
      "city": "Sydney",
      "state": "New South Wales",
      "region_code": "NSW",
      "postal_code": "1140"
    }
  },
  {
    "user": {
      "first_name": "Dotty",
      "last_name": "Iveans",
      "email": "diveans0@noaa.gov",
      "phone": "1388060503"
    },
    "address": {
      "street_address": "1186 Dayton Alley",
      "city": "Sydney",
      "state": "New South Wales",
      "region_code": "NSW",
      "postal_code": "1028"
    }
  },
  {
    "user": {
      "first_name": "Almeria",
      "last_name": "Hefner",
      "email": "ahefner0@studiopress.com",
      "phone": "1685660682"
    },
    "address": {
      "street_address": "27 Cherokee Lane",
      "city": "Launceston",
      "state": "Tasmania",
      "region_code": "TAS",
      "postal_code": "7904"
    }
  },
  {
    "user": {
      "first_name": "Kizzee",
      "last_name": "Bellin",
      "email": "kbellin0@mac.com",
      "phone": "5074914028"
    },
    "address": {
      "street_address": "6 Straubel Parkway",
      "city": "Launceston",
      "state": "Tasmania",
      "region_code": "TAS",
      "postal_code": "7916"
    }
  },
  {
    "user": {
      "first_name": "Luz",
      "last_name": "Hof",
      "email": "lhof0@usa.gov",
      "phone": "8834455802"
    },
    "address": {
      "street_address": "83516 Fairfield Avenue",
      "city": "Adelaide Mail Centre",
      "state": "South Australia",
      "region_code": "SA",
      "postal_code": "5869"
    }
  },
  {
    "user": {
      "first_name": "Hestia",
      "last_name": "Heningham",
      "email": "hheningham0@ameblo.jp",
      "phone": "3983073975"
    },
    "address": {
      "street_address": "6707 Eggendart Park",
      "city": "Sydney",
      "state": "New South Wales",
      "region_code": "NSW",
      "postal_code": "1196"
    }
  },
  {
    "user": {
      "first_name": "Rip",
      "last_name": "Addeycott",
      "email": "raddeycott0@usnews.com",
      "phone": "8886011597"
    },
    "address": {
      "street_address": "9 Pawling Trail",
      "city": "Adelaide",
      "state": "South Australia",
      "region_code": "SA",
      "postal_code": "5839"
    }
  },
  {
    "user": {
      "first_name": "Kaine",
      "last_name": "Carneck",
      "email": "kcarneck0@chronoengine.com",
      "phone": "9532754242"
    },
    "address": {
      "street_address": "862 Ohio Trail",
      "city": "Sydney",
      "state": "New South Wales",
      "region_code": "NSW",
      "postal_code": "1161"
    }
  },
  {
    "user": {
      "first_name": "Caresse",
      "last_name": "Goddman",
      "email": "cgoddman0@mozilla.org",
      "phone": "5816126938"
    },
    "address": {
      "street_address": "0 La Follette Avenue",
      "city": "Launceston",
      "state": "Tasmania",
      "region_code": "TAS",
      "postal_code": "7904"
    }
  },
  {
    "user": {
      "first_name": "Yevette",
      "last_name": "Healks",
      "email": "yhealks0@macromedia.com",
      "phone": "5897577604"
    },
    "address": {
      "street_address": "88 Springview Center",
      "city": "Adelaide",
      "state": "South Australia",
      "region_code": "SA",
      "postal_code": "5839"
    }
  },
  {
    "user": {
      "first_name": "Bessie",
      "last_name": "Easterfield",
      "email": "beasterfield0@aol.com",
      "phone": "1885441565"
    },
    "address": {
      "street_address": "0 Calypso Alley",
      "city": "Perth",
      "state": "Western Australia",
      "region_code": "WA",
      "postal_code": "6817"
    }
  },
  {
    "user": {
      "first_name": "Saundra",
      "last_name": "Brunesco",
      "email": "sbrunesco0@blogspot.com",
      "phone": "2673108158"
    },
    "address": {
      "street_address": "8476 Namekagon Trail",
      "city": "Launceston",
      "state": "Tasmania",
      "region_code": "TAS",
      "postal_code": "7904"
    }
  },
  {
    "user": {
      "first_name": "Nicol",
      "last_name": "Studdal",
      "email": "nstuddal0@spiegel.de",
      "phone": "9778755421"
    },
    "address": {
      "street_address": "83 Westend Circle",
      "city": "Sydney",
      "state": "New South Wales",
      "region_code": "NSW",
      "postal_code": "1196"
    }
  },
  {
    "user": {
      "first_name": "Priscilla",
      "last_name": "Blakebrough",
      "email": "pblakebrough0@networkadvertising.org",
      "phone": "2904498805"
    },
    "address": {
      "street_address": "109 Delladonna Place",
      "city": "Launceston",
      "state": "Tasmania",
      "region_code": "TAS",
      "postal_code": "7916"
    }
  },
  {
    "user": {
      "first_name": "Zaneta",
      "last_name": "Spurling",
      "email": "zspurling0@studiopress.com",
      "phone": "7363358156"
    },
    "address": {
      "street_address": "27 Dexter Crossing",
      "city": "Hobart",
      "state": "Tasmania",
      "region_code": "TAS",
      "postal_code": "7803"
    }
  },
  {
    "user": {
      "first_name": "Rhianon",
      "last_name": "Isaacson",
      "email": "risaacson0@utexas.edu",
      "phone": "1232113555"
    },
    "address": {
      "street_address": "977 Schmedeman Crossing",
      "city": "Launceston",
      "state": "Tasmania",
      "region_code": "TAS",
      "postal_code": "7916"
    }
  },
  {
    "user": {
      "first_name": "Paton",
      "last_name": "Falconer-Taylor",
      "email": "pfalconertaylor0@sfgate.com",
      "phone": "2686427123"
    },
    "address": {
      "street_address": "3114 Mendota Street",
      "city": "Launceston",
      "state": "Tasmania",
      "region_code": "TAS",
      "postal_code": "7904"
    }
  },
  {
    "user": {
      "first_name": "Aurelia",
      "last_name": "O'Glassane",
      "email": "aoglassane0@hhs.gov",
      "phone": "8749523062"
    },
    "address": {
      "street_address": "650 Kingsford Point",
      "city": "Sydney",
      "state": "New South Wales",
      "region_code": "NSW",
      "postal_code": "1120"
    }
  },
  {
    "user": {
      "first_name": "Dale",
      "last_name": "Bulfit",
      "email": "dbulfit0@nationalgeographic.com",
      "phone": "6399641206"
    },
    "address": {
      "street_address": "06670 Summit Junction",
      "city": "Sydney",
      "state": "New South Wales",
      "region_code": "NSW",
      "postal_code": "1181"
    }
  },
  {
    "user": {
      "first_name": "Yank",
      "last_name": "Woodbridge",
      "email": "ywoodbridge0@msu.edu",
      "phone": "7695493324"
    },
    "address": {
      "street_address": "2 Stang Parkway",
      "city": "Sydney",
      "state": "New South Wales",
      "region_code": "NSW",
      "postal_code": "1161"
    }
  },
  {
    "user": {
      "first_name": "Wells",
      "last_name": "Garfitt",
      "email": "wgarfitt0@example.com",
      "phone": "9208695249"
    },
    "address": {
      "street_address": "7222 Mariners Cove Crossing",
      "city": "Sydney",
      "state": "New South Wales",
      "region_code": "NSW",
      "postal_code": "1130"
    }
  },
  {
    "user": {
      "first_name": "Tammy",
      "last_name": "Dubock",
      "email": "tdubock0@tuttocitta.it",
      "phone": "9493579701"
    },
    "address": {
      "street_address": "04038 Farwell Hill",
      "city": "Australia Square",
      "state": "New South Wales",
      "region_code": "NSW",
      "postal_code": "1213"
    }
  }
]
